gerbonara/NOTES
gerbonara/__init__.py
gerbonara/__main__.py
gerbonara/apertures.py
gerbonara/cam.py
gerbonara/cli.py
gerbonara/excellon.py
gerbonara/graphic_objects.py
gerbonara/graphic_primitives.py
gerbonara/ipc356.py
gerbonara/layer_rules.py
gerbonara/layers.py
gerbonara/newstroke.py
gerbonara/rs274x.py
gerbonara/utils.py
gerbonara/aperture_macros/__init__.py
gerbonara/aperture_macros/expression.py
gerbonara/aperture_macros/parse.py
gerbonara/aperture_macros/primitive.py
gerbonara/cad/__init__.py
gerbonara/cad/breakout.py
gerbonara/cad/primitives.py
gerbonara/cad/protoboard.py
gerbonara/cad/protoserve.py
gerbonara/cad/data/__init__.py
gerbonara/cad/data/center-pad-spikes.kicad_mod
gerbonara/cad/data/pad-between-spiked.kicad_mod
gerbonara/cad/data/tht-0.8.kicad_mod
gerbonara/cad/kicad/__init__.py
gerbonara/cad/kicad/base_types.py
gerbonara/cad/kicad/footprints.py
gerbonara/cad/kicad/graphical_primitives.py
gerbonara/cad/kicad/layer_colors.py
gerbonara/cad/kicad/pcb.py
gerbonara/cad/kicad/primitives.py
gerbonara/cad/kicad/schematic.py
gerbonara/cad/kicad/schematic_colors.py
gerbonara/cad/kicad/sexp.py
gerbonara/cad/kicad/sexp_mapper.py
gerbonara/cad/kicad/symbols.py
gerbonara/cad/kicad/tmtheme.py
gerbonara/cad/protoserve_data/__init__.py
gerbonara/cad/protoserve_data/protoserve.html
gerbonara/data/__init__.py
gerbonara/data/newstroke_font.cpp
gerbonara/tests/__init__.py
gerbonara/tests/conftest.py
gerbonara/tests/image_support.py
gerbonara/tests/test_cli.py
gerbonara/tests/test_excellon.py
gerbonara/tests/test_ipc356.py
gerbonara/tests/test_kicad_footprints.py
gerbonara/tests/test_kicad_sexpr.py
gerbonara/tests/test_kicad_symbols.py
gerbonara/tests/test_layers.py
gerbonara/tests/test_rs274x.py
gerbonara/tests/test_utils.py
gerbonara/tests/utils.py
gerbonara-1.5.0.dist-info/LICENSE
gerbonara-1.5.0.dist-info/METADATA
gerbonara-1.5.0.dist-info/WHEEL
gerbonara-1.5.0.dist-info/entry_points.txt
gerbonara-1.5.0.dist-info/top_level.txt
gerbonara-1.5.0.dist-info/RECORD
