Metadata-Version: 2.1
Name: gerbonara
Version: 1.5.0
Summary: Tools to handle Gerber and Excellon files in Python
Home-page: https://gitlab.com/gerbolyze/gerbonara
Author: jaseg, XenGi
Author-email: gerbonara@jaseg.de
Project-URL: Documentation, https://gerbolyze.gitlab.io/gerbonara/
Project-URL: Source, https://gitlab.com/gerbolyze/gerbonara
Project-URL: Tracker, https://gitlab.com/gerbolyze/gerbonara/issues
Keywords: gerber excellon pcb
Classifier: Development Status :: 4 - Beta
Classifier: Environment :: Console
Classifier: Intended Audience :: Developers
Classifier: Intended Audience :: Information Technology
Classifier: Intended Audience :: Manufacturing
Classifier: Intended Audience :: Science/Research
Classifier: License :: OSI Approved :: Apache Software License
Classifier: Natural Language :: English
Classifier: Operating System :: POSIX :: Linux
Classifier: Programming Language :: Python :: 3
Classifier: Programming Language :: Python :: 3 :: Only
Classifier: Programming Language :: Python :: 3.10
Classifier: Programming Language :: Python :: 3.11
Classifier: Topic :: Artistic Software
Classifier: Topic :: Multimedia :: Graphics
Classifier: Topic :: Printing
Classifier: Topic :: Scientific/Engineering
Classifier: Topic :: Scientific/Engineering :: Electronic Design Automation (EDA)
Classifier: Topic :: Scientific/Engineering :: Image Processing
Classifier: Topic :: Utilities
Classifier: Typing :: Typed
Requires-Python: >=3.10
License-File: LICENSE
